stacks_twitter/__init__.py
stacks_twitter/admin.py
stacks_twitter/apps.py
stacks_twitter/fields.py
stacks_twitter/forms.py
stacks_twitter/models.py
stacks_twitter/serializers.py
stacks_twitter/stuff.py
stacks_twitter/utils.py
stacks_twitter/migrations/0001_initial.py
stacks_twitter/migrations/0002_auto_20150529_2033.py
stacks_twitter/migrations/0003_auto_20150602_1342.py
stacks_twitter/migrations/__init__.py
stacks_twitter/templates/stacks_twitter/tweet/tweet-full_width.html
stacks_twitter-0.1.1.dist-info/DESCRIPTION.rst
stacks_twitter-0.1.1.dist-info/LICENSE.txt
stacks_twitter-0.1.1.dist-info/METADATA
stacks_twitter-0.1.1.dist-info/RECORD
stacks_twitter-0.1.1.dist-info/WHEEL
stacks_twitter-0.1.1.dist-info/metadata.json
stacks_twitter-0.1.1.dist-info/top_level.txt
